leaf_register/__init__.py
leaf_register/abstract_leaf.py
leaf_register/equipment_actions.yaml
leaf_register/equipment_data.yaml
leaf_register/metadata.py
leaf_register/py.typed
leaf_register/topic_utilities.py
leaf_register-0.1.2.dist-info/METADATA
leaf_register-0.1.2.dist-info/WHEEL
leaf_register-0.1.2.dist-info/RECORD
