Metadata-Version: 2.3
Name: leaf-register
Version: 0.1.2
Summary: Registry system for the LEAF framework
License: Apache-2.0
Author: Matthew Crowther
Author-email: M.Crowther1@newcastle.ac.uk
Requires-Python: >=3.12,<4.0
Classifier: License :: OSI Approved :: Apache Software License
Classifier: Programming Language :: Python :: 3
Classifier: Programming Language :: Python :: 3.12
Classifier: Programming Language :: Python :: 3.13
